{"name":"eKuiper","homepage_url":"https://ekuiper.org","repo_url":"https://github.com/lf-edge/ekuiper","logo":"wasm.svg","crunchbase":"https://www.crunchbase.com/organization/linux-foundation-edge","github_data":{"languages":[{"name":"Go","value":3500770,"color":"#00ADD8"},{"name":"C","value":51097,"color":"#555555"},{"name":"Shell","value":38393,"color":"#89e051"},{"name":"Python","value":32449,"color":"#3572A5"},{"name":"Makefile","value":12079,"color":"#427819"},{"name":"Mustache","value":2129},{"name":"Dockerfile","value":1782,"color":"#384d54"}],"contributions":"12;4;9;22;8;12;14;12;26;5;9;11;16;4;11;10;8;0;7;7;6;3;13;8;20;20;14;23;20;16;19;12;38;27;17;15;20;9;9;24;23;11;17;11;13;14;20;2;10;11;8;9","firstWeek":"2022-10-02Z","stars":1153,"license":"Apache License 2.0","description":"Lightweight data stream processing engine for IoT edge","latest_commit_date":"2023-09-22T05:49:17Z","latest_commit_link":"/lf-edge/ekuiper/commit/025a1ceb0a0bc3ac38c6baac6f94682d272037bf","release_date":"2023-09-22T06:15:06Z","release_link":"https://github.com/lf-edge/ekuiper/releases","contributors_count":75,"contributors_link":"https://github.com/lf-edge/ekuiper/graphs/contributors"},"repos":[{"url":"https://github.com/lf-edge/ekuiper","stars":1153}],"github_start_commit_data":{"start_commit_link":"/lf-edge/ekuiper/commit/6823b05a14e1899956a6eb49fab2013516195b31","start_date":"2019-07-03T07:37:13Z"},"image_data":{"fileName":"e-kuiper.svg","hash":"3DpcF5SM60VprmRQqnY8EHbkjaBWoeXv4OwCSTqrDDo="},"firstCommitDate":"2019-07-03T07:37:13Z","firstCommitLink":"https://github.com/lf-edge/ekuiper/commit/6823b05a14e1899956a6eb49fab2013516195b31","latestCommitDate":{"text":"3 months ago","value":"940","original":"2023-09-22T05:49:17Z"},"latestCommitLink":"https://github.com/lf-edge/ekuiper/commit/025a1ceb0a0bc3ac38c6baac6f94682d272037bf","releaseDate":{"text":"3 months ago","value":"940","original":"2023-09-22T06:15:06Z"},"releaseLink":"https://github.com/lf-edge/ekuiper/releases","commitsThisYear":689,"contributorsCount":75,"contributorsLink":"https://github.com/lf-edge/ekuiper/graphs/contributors","language":"Go","stars":1153,"license":"Apache License 2.0","headquarters":"Bouvet Island, Antarctica","twitter":"https://twitter.com/CloudNativeFdn","description":"Lightweight data stream processing engine for IoT edge","organization":"Non-Public Unnamed Organization","crunchbaseData":{"name":"Non-Public Unnamed Organization","homepage":"https://www.cncf.io","city":"Bouvet Island","region":"Antarctica","country":"Antarctica","twitter":"https://twitter.com/CloudNativeFdn","parents":[],"linkedin":null},"path":"Wasm / Embedded Functions","landscape":"Wasm / Embedded Functions","category":"Wasm","amount":"N/A","oss":true,"href":"logos/e-kuiper.svg","bestPracticeBadgeId":false,"bestPracticePercentage":null,"industries":[],"enduser":false,"starsPresent":true,"starsAsText":"1,153","marketCapPresent":false,"marketCapAsText":"N/A","id":"e-kuiper","flatName":"eKuiper","member":false,"relation":false,"isSubsidiaryProject":false}