{"name":"OPA","homepage_url":"https://www.openpolicyagent.org/","repo_url":"https://github.com/open-policy-agent/opa","logo":"opa.svg","crunchbase":"https://www.crunchbase.com/organization/cloud-native-computing-foundation","allow_duplicate_repo":true,"github_data":{"languages":[{"name":"Go","value":6463202,"color":"#00ADD8"},{"name":"C","value":934493,"color":"#555555"},{"name":"C++","value":707222,"color":"#f34b7d"},{"name":"Open Policy Agent","value":25693},{"name":"Makefile","value":22546,"color":"#427819"},{"name":"Shell","value":18495,"color":"#89e051"},{"name":"JavaScript","value":14203,"color":"#f1e05a"},{"name":"Python","value":5616,"color":"#3572A5"},{"name":"Dockerfile","value":2835,"color":"#384d54"}],"contributions":"11;10;17;16;20;24;6;19;6;10;20;6;11;0;29;5;3;13;9;9;11;17;17;20;16;12;11;8;4;7;13;8;2;13;11;6;17;19;16;22;7;6;10;11;7;6;10;8;13;6;7;7","firstWeek":"2022-10-02Z","stars":8496,"license":"Apache License 2.0","description":"An open source, general-purpose policy engine.","latest_commit_date":"2023-09-23T19:29:49Z","latest_commit_link":"/open-policy-agent/opa/commit/b07e60a9f8d1cfe045385ee2196908da63c816df","release_date":"2023-08-31T14:40:27Z","release_link":"https://github.com/open-policy-agent/opa/releases","contributors_count":420,"contributors_link":"https://github.com/open-policy-agent/opa/graphs/contributors"},"repos":[{"url":"https://github.com/open-policy-agent/opa","stars":8496}],"github_start_commit_data":{"start_commit_link":"/open-policy-agent/opa/commit/7eb56674c51d286afa134861ba282bf7a13668c6","start_date":"2015-12-28T22:08:25Z"},"image_data":{"fileName":"opa.svg","hash":"1tC4W5h6uvHUbgyUMfw6qLf6VLngchvlURGNNNLuDzM="},"firstCommitDate":"2015-12-28T22:08:25Z","firstCommitLink":"https://github.com/open-policy-agent/opa/commit/7eb56674c51d286afa134861ba282bf7a13668c6","latestCommitDate":{"text":"3 months ago","value":"940","original":"2023-09-23T19:29:49Z"},"latestCommitLink":"https://github.com/open-policy-agent/opa/commit/b07e60a9f8d1cfe045385ee2196908da63c816df","releaseDate":{"text":"4 months ago","value":"930","original":"2023-08-31T14:40:27Z"},"releaseLink":"https://github.com/open-policy-agent/opa/releases","commitsThisYear":592,"contributorsCount":420,"contributorsLink":"https://github.com/open-policy-agent/opa/graphs/contributors","language":"Go","stars":8496,"license":"Apache License 2.0","headquarters":"Bouvet Island, Antarctica","twitter":"https://twitter.com/CloudNativeFdn","description":"An open source, general-purpose policy engine.","organization":"Non-Public Unnamed Organization","crunchbaseData":{"name":"Non-Public Unnamed Organization","homepage":"https://www.cncf.io","city":"Bouvet Island","region":"Antarctica","country":"Antarctica","twitter":"https://twitter.com/CloudNativeFdn","parents":[],"linkedin":null},"path":"Wasm / Embedded Functions","landscape":"Wasm / Embedded Functions","category":"Wasm","amount":"N/A","oss":true,"href":"logos/opa.svg","bestPracticeBadgeId":1768,"bestPracticePercentage":100,"industries":[],"enduser":false,"starsPresent":true,"starsAsText":"8,496","marketCapPresent":false,"marketCapAsText":"N/A","id":"opa","flatName":"OPA","member":false,"relation":"member","isSubsidiaryProject":true}